nb_g2p-2.1.1.dist-info/METADATA
nb_g2p-2.1.1.dist-info/WHEEL
nb_g2p-2.1.1.dist-info/entry_points.txt
nb_g2p-2.1.1.dist-info/licenses/LICENSE
nb_g2p/__init__.py
nb_g2p/evaluate.py
nb_g2p/g2p_stats.py
nb_g2p/utils.py
nb_g2p-2.1.1.dist-info/RECORD
