Metadata-Version: 2.1
Name: nb_g2p
Version: 2.1.1
Summary: Transcribe Norwegian dialects phonemically from bokmål text.
Author-Email: =?utf-8?q?Spr=C3=A5kbanken?= <sprakbanken@nb.no>, Ingerid Dale <ingerid.dale@nb.no>, =?utf-8?q?Marie_Iversdatter_R=C3=B8sok?= <marie.rosok@nb.no>
License: CC0
Requires-Python: >=3.11
Requires-Dist: Levenshtein
Requires-Dist: convert-pa>=1.0.0
Requires-Dist: google-cloud-storage
Requires-Dist: phonetisaurus
